{
    "data": {
        "markdownRemark": {
            "fields": {
                "title": "gatsby-source-filesystem"
            },
            "html": "<h1 id=\"gatsby-source-filesystem\"><a href=\"#gatsby-source-filesystem\" aria-hidden=\"true\" class=\"anchor\"><svg aria-hidden=\"true\" height=\"16\" version=\"1.1\" viewBox=\"0 0 16 16\" width=\"16\"><path fill-rule=\"evenodd\" d=\"M4 9h1v1H4c-1.5 0-3-1.69-3-3.5S2.55 3 4 3h4c1.45 0 3 1.69 3 3.5 0 1.41-.91 2.72-2 3.25V8.59c.58-.45 1-1.27 1-2.09C10 5.22 8.98 4 8 4H4c-.98 0-2 1.22-2 2.5S3 9 4 9zm9-3h-1v1h1c1 0 2 1.22 2 2.5S13.98 12 13 12H9c-.98 0-2-1.22-2-2.5 0-.83.42-1.64 1-2.09V6.25c-1.09.53-2 1.84-2 3.25C6 11.31 7.55 13 9 13h4c1.45 0 3-1.69 3-3.5S14.5 6 13 6z\"></path></svg></a>gatsby-source-filesystem</h1>\n<p>Plugin for creating <code>File</code> nodes from the file system. The various\n“transformer” plugins transform <code>File</code> nodes into various other types of data\ne.g. <code>gatsby-transformer-json</code> transforms JSON files into JSON data nodes and\n<code>gatsby-transformer-remark</code> transforms markdown files into <code>MarkdownRemark</code>\nnodes from which you can query an HTML representation of the markdown.</p>\n<h2 id=\"install\"><a href=\"#install\" aria-hidden=\"true\" class=\"anchor\"><svg aria-hidden=\"true\" height=\"16\" version=\"1.1\" viewBox=\"0 0 16 16\" width=\"16\"><path fill-rule=\"evenodd\" d=\"M4 9h1v1H4c-1.5 0-3-1.69-3-3.5S2.55 3 4 3h4c1.45 0 3 1.69 3 3.5 0 1.41-.91 2.72-2 3.25V8.59c.58-.45 1-1.27 1-2.09C10 5.22 8.98 4 8 4H4c-.98 0-2 1.22-2 2.5S3 9 4 9zm9-3h-1v1h1c1 0 2 1.22 2 2.5S13.98 12 13 12H9c-.98 0-2-1.22-2-2.5 0-.83.42-1.64 1-2.09V6.25c-1.09.53-2 1.84-2 3.25C6 11.31 7.55 13 9 13h4c1.45 0 3-1.69 3-3.5S14.5 6 13 6z\"></path></svg></a>Install</h2>\n<p><code>npm install --save gatsby-source-filesystem</code></p>\n<h2 id=\"how-to-use\"><a href=\"#how-to-use\" aria-hidden=\"true\" class=\"anchor\"><svg aria-hidden=\"true\" height=\"16\" version=\"1.1\" viewBox=\"0 0 16 16\" width=\"16\"><path fill-rule=\"evenodd\" d=\"M4 9h1v1H4c-1.5 0-3-1.69-3-3.5S2.55 3 4 3h4c1.45 0 3 1.69 3 3.5 0 1.41-.91 2.72-2 3.25V8.59c.58-.45 1-1.27 1-2.09C10 5.22 8.98 4 8 4H4c-.98 0-2 1.22-2 2.5S3 9 4 9zm9-3h-1v1h1c1 0 2 1.22 2 2.5S13.98 12 13 12H9c-.98 0-2-1.22-2-2.5 0-.83.42-1.64 1-2.09V6.25c-1.09.53-2 1.84-2 3.25C6 11.31 7.55 13 9 13h4c1.45 0 3-1.69 3-3.5S14.5 6 13 6z\"></path></svg></a>How to use</h2>\n<pre><code class=\"language-javascript\"><span class=\"token comment\" spellcheck=\"true\">// In your gatsby-config.js</span>\nplugins<span class=\"token punctuation\">:</span> <span class=\"token punctuation\">[</span>\n  <span class=\"token comment\" spellcheck=\"true\">// You can have multiple instances of this plugin</span>\n  <span class=\"token comment\" spellcheck=\"true\">// to read source nodes from different locations on your</span>\n  <span class=\"token comment\" spellcheck=\"true\">// filesystem.</span>\n  <span class=\"token comment\" spellcheck=\"true\">//</span>\n  <span class=\"token comment\" spellcheck=\"true\">// The following sets up the Jekyll pattern of having a</span>\n  <span class=\"token comment\" spellcheck=\"true\">// \"pages\" directory for Markdown files and a \"data\" directory</span>\n  <span class=\"token comment\" spellcheck=\"true\">// for `.json`, `.yaml`, `.csv`.</span>\n  <span class=\"token punctuation\">{</span>\n    resolve<span class=\"token punctuation\">:</span> <span class=\"token template-string\"><span class=\"token string\">`gatsby-source-filesystem`</span></span><span class=\"token punctuation\">,</span>\n    options<span class=\"token punctuation\">:</span> <span class=\"token punctuation\">{</span>\n      name<span class=\"token punctuation\">:</span> <span class=\"token template-string\"><span class=\"token string\">`docs`</span></span><span class=\"token punctuation\">,</span>\n      path<span class=\"token punctuation\">:</span> <span class=\"token template-string\"><span class=\"token string\">`</span><span class=\"token interpolation\"><span class=\"token interpolation-punctuation punctuation\">${</span>__dirname<span class=\"token interpolation-punctuation punctuation\">}</span></span><span class=\"token string\">/pages/`</span></span><span class=\"token punctuation\">,</span>\n    <span class=\"token punctuation\">}</span><span class=\"token punctuation\">,</span>\n  <span class=\"token punctuation\">}</span><span class=\"token punctuation\">,</span>\n  <span class=\"token punctuation\">{</span>\n    resolve<span class=\"token punctuation\">:</span> <span class=\"token template-string\"><span class=\"token string\">`gatsby-source-filesystem`</span></span><span class=\"token punctuation\">,</span>\n    options<span class=\"token punctuation\">:</span> <span class=\"token punctuation\">{</span>\n      name<span class=\"token punctuation\">:</span> <span class=\"token template-string\"><span class=\"token string\">`packages`</span></span><span class=\"token punctuation\">,</span>\n      path<span class=\"token punctuation\">:</span> <span class=\"token template-string\"><span class=\"token string\">`</span><span class=\"token interpolation\"><span class=\"token interpolation-punctuation punctuation\">${</span>__dirname<span class=\"token interpolation-punctuation punctuation\">}</span></span><span class=\"token string\">/data/`</span></span><span class=\"token punctuation\">,</span>\n    <span class=\"token punctuation\">}</span><span class=\"token punctuation\">,</span>\n  <span class=\"token punctuation\">}</span><span class=\"token punctuation\">,</span>\n<span class=\"token punctuation\">]</span></code></pre>\n<h2 id=\"how-to-query\"><a href=\"#how-to-query\" aria-hidden=\"true\" class=\"anchor\"><svg aria-hidden=\"true\" height=\"16\" version=\"1.1\" viewBox=\"0 0 16 16\" width=\"16\"><path fill-rule=\"evenodd\" d=\"M4 9h1v1H4c-1.5 0-3-1.69-3-3.5S2.55 3 4 3h4c1.45 0 3 1.69 3 3.5 0 1.41-.91 2.72-2 3.25V8.59c.58-.45 1-1.27 1-2.09C10 5.22 8.98 4 8 4H4c-.98 0-2 1.22-2 2.5S3 9 4 9zm9-3h-1v1h1c1 0 2 1.22 2 2.5S13.98 12 13 12H9c-.98 0-2-1.22-2-2.5 0-.83.42-1.64 1-2.09V6.25c-1.09.53-2 1.84-2 3.25C6 11.31 7.55 13 9 13h4c1.45 0 3-1.69 3-3.5S14.5 6 13 6z\"></path></svg></a>How to query</h2>\n<p>You can query file nodes like the following:</p>\n<pre><code class=\"language-graphql\"><span class=\"token punctuation\">{</span>\n  allFile <span class=\"token punctuation\">{</span>\n    edges <span class=\"token punctuation\">{</span>\n      node <span class=\"token punctuation\">{</span>\n        extension\n        dir\n        modifyDate\n      <span class=\"token punctuation\">}</span>\n    <span class=\"token punctuation\">}</span>\n  <span class=\"token punctuation\">}</span>\n<span class=\"token punctuation\">}</span></code></pre>"
        }
    },
    "pathContext": {
        "slug": "/docs/packages/gatsby-source-filesystem/"
    }
}